.DS_Store
outline_api/__init__.py
outline_api/errors.py
outline_api/outline_api.py
outline_api/prometheus.py
outline_api-0.0.6.dist-info/LICENSE.txt
outline_api-0.0.6.dist-info/METADATA
outline_api-0.0.6.dist-info/WHEEL
outline_api-0.0.6.dist-info/top_level.txt
outline_api-0.0.6.dist-info/RECORD
