Metadata-Version: 2.1
Name: outline-api
Version: 0.0.6
Summary: A wrapper library to facilitate the access to Outline VPN as well as its Prometheus APIs on Outline VPN Servers.
Home-page: https://github.com/ASL-19/outline-api
Author: ASL19 Software Development Team
Author-email: dev@asl19.org
License: GPLv3
Keywords: Outline,Outline Manager,Outline VPN,Outline API
Classifier: Development Status :: 5 - Production/Stable
Classifier: Intended Audience :: Developers
Classifier: Topic :: Software Development :: Build Tools
Classifier: License :: OSI Approved :: GNU General Public License (GPL)
Classifier: Operating System :: OS Independent
Classifier: Programming Language :: Python :: 3
Classifier: Programming Language :: Python :: 3.4
Classifier: Programming Language :: Python :: 3.5
Classifier: Programming Language :: Python :: 3.6
Classifier: Programming Language :: Python :: 3.7
Classifier: Programming Language :: Python :: 3.8
License-File: LICENSE.txt
Requires-Dist: requests
